beaker_bunsen/__about__.py
beaker_bunsen/__init__.py
beaker_bunsen/bunsen_agent.py
beaker_bunsen/bunsen_context.py
beaker_bunsen/builder/__init__.py
beaker_bunsen/builder/bunsen_context.py
beaker_bunsen/builder/bunsen_package.py
beaker_bunsen/corpus/__init__.py
beaker_bunsen/corpus/corpus.py
beaker_bunsen/corpus/protocols.py
beaker_bunsen/corpus/types.py
beaker_bunsen/corpus/embedders/__init__.py
beaker_bunsen/corpus/embedders/embedder.py
beaker_bunsen/corpus/loaders/__init__.py
beaker_bunsen/corpus/loaders/base.py
beaker_bunsen/corpus/loaders/code_library_loader.py
beaker_bunsen/corpus/loaders/local_file_loader.py
beaker_bunsen/corpus/loaders/schemes.py
beaker_bunsen/corpus/resources/__init__.py
beaker_bunsen/corpus/resources/resource.py
beaker_bunsen/corpus/resources/splitting.py
beaker_bunsen/corpus/util/__init__.py
beaker_bunsen/corpus/util/helpers.py
beaker_bunsen/corpus/util/logging.py
beaker_bunsen/corpus/util/splitters.py
beaker_bunsen/corpus/vector_stores/__init__.py
beaker_bunsen/corpus/vector_stores/base_vector_store.py
beaker_bunsen/corpus/vector_stores/chromadb_store.py
beaker_bunsen/scripts/__init__.py
beaker_bunsen/scripts/bunsen.py
beaker_bunsen/scripts/extract_documentation.py
beaker_bunsen/scripts/extract_examples.py
beaker_bunsen/scripts/helpers.py
beaker_bunsen-0.0.13.data/data/share/beaker/commands/beaker_bunsen.json
beaker_bunsen-0.0.13.dist-info/METADATA
beaker_bunsen-0.0.13.dist-info/WHEEL
beaker_bunsen-0.0.13.dist-info/entry_points.txt
beaker_bunsen-0.0.13.dist-info/licenses/LICENSE.txt
beaker_bunsen-0.0.13.dist-info/RECORD
