Metadata-Version: 2.3
Name: beaker-bunsen
Version: 0.0.13
Summary: Quickly generate new Beaker contexts for new domains and libraries.
Project-URL: Documentation, https://github.com/unknown/beaker-bunsen#readme
Project-URL: Issues, https://github.com/unknown/beaker-bunsen/issues
Project-URL: Source, https://github.com/unknown/beaker-bunsen
Author-email: Matthew Printz <matt@jataware.com>
License-Expression: MIT
License-File: LICENSE.txt
Classifier: Development Status :: 4 - Beta
Classifier: Programming Language :: Python
Classifier: Programming Language :: Python :: 3.10
Classifier: Programming Language :: Python :: 3.11
Classifier: Programming Language :: Python :: 3.12
Classifier: Programming Language :: Python :: Implementation :: CPython
Classifier: Programming Language :: Python :: Implementation :: PyPy
Requires-Python: >=3.10
Requires-Dist: archytas~=1.1.8
Requires-Dist: beaker-kernel~=1.6.1
Requires-Dist: beautifulsoup4
Requires-Dist: chromadb~=0.4.22
Requires-Dist: click~=8.1.7
Requires-Dist: hatchling
Requires-Dist: marko~=2.0.3
Requires-Dist: numpy<2.0
Requires-Dist: tenacity~=8.2.3
Requires-Dist: tiktoken~=0.5.2
